src/__init__.py
src/cli_interface.py
src/main.py
src/core/__init__.py
src/core/bt_file.py
src/core/bt_graph.py
src/core/bt_module.py
src/plantuml/__init__.py
src/plantuml/plantuml_file_creator.py
BT_diagrams-0.0.10.dist-info/METADATA
BT_diagrams-0.0.10.dist-info/WHEEL
BT_diagrams-0.0.10.dist-info/entry_points.txt
BT_diagrams-0.0.10.dist-info/top_level.txt
BT_diagrams-0.0.10.dist-info/RECORD
