Metadata-Version: 2.1
Name: BT-diagrams
Version: 0.0.10
Summary: Thesis project
Home-page: https://github.com/Perlten/Master-thesis-rename
Author: Nikolai Perlt
Author-email: npe@itu.dk
Classifier: Programming Language :: Python :: 3.10
Requires-Dist: plantuml
Requires-Dist: typer
Requires-Dist: astroid
Requires-Dist: six
Requires-Dist: requests
Requires-Dist: jsonschema
